ecospy/EcosParameterSet.py
ecospy/EcosSimulation.py
ecospy/EcosSimulationRunner.py
ecospy/EcosSimulationStructure.py
ecospy/__init__.py
ecospy/lib.py
ecospy/plotter.py
ecospy/binaries/ecos
ecospy/binaries/ecos.exe
ecospy/binaries/libecosc.dll
ecospy/binaries/libecosc.so
ecospy/binaries/proxyfmu
ecospy/binaries/proxyfmu.exe
ecospy-0.7.0.data/data/Scripts/ecos
ecospy-0.7.0.data/data/Scripts/ecos.exe
ecospy-0.7.0.data/data/Scripts/proxyfmu
ecospy-0.7.0.data/data/Scripts/proxyfmu.exe
ecospy-0.7.0.dist-info/licenses/LICENSE
ecospy-0.7.0.dist-info/METADATA
ecospy-0.7.0.dist-info/WHEEL
ecospy-0.7.0.dist-info/top_level.txt
ecospy-0.7.0.dist-info/RECORD
